{
  "swagger": "2.0",
  "info": {
    "title": "Streamfair Identity Provider",
    "version": "1.0",
    "contact": {
      "name": "Streamfair",
      "url": "https://github.com/Streamfair",
      "email": "nelix@posteo.de"
    }
  },
  "tags": [
    {
      "name": "IdentityProvider"
    }
  ],
  "consumes": [
    "application/json"
  ],
  "produces": [
    "application/json"
  ],
  "paths": {
    "/streamfair/v1/login_user_account": {
      "post": {
        "summary": "add summary here",
        "description": "add description here",
        "operationId": "IdentityProvider_LoginUserAccount",
        "responses": {
          "200": {
            "description": "A successful response.",
            "schema": {
              "$ref": "#/definitions/pbLoginUserAccountResponse"
            }
          },
          "default": {
            "description": "An unexpected error response.",
            "schema": {
              "$ref": "#/definitions/rpcStatus"
            }
          }
        },
        "parameters": [
          {
            "name": "body",
            "in": "body",
            "required": true,
            "schema": {
              "$ref": "#/definitions/pbLoginUserAccountRequest"
            }
          }
        ],
        "tags": [
          "IdentityProvider"
        ]
      }
    },
    "/streamfair/v1/register_user_account": {
      "post": {
        "summary": "add summary here",
        "description": "add description here",
        "operationId": "IdentityProvider_RegisterUserAccount",
        "responses": {
          "200": {
            "description": "A successful response.",
            "schema": {
              "$ref": "#/definitions/pbRegisterUserAccountResponse"
            }
          },
          "default": {
            "description": "An unexpected error response.",
            "schema": {
              "$ref": "#/definitions/rpcStatus"
            }
          }
        },
        "parameters": [
          {
            "name": "body",
            "in": "body",
            "required": true,
            "schema": {
              "$ref": "#/definitions/pbRegisterUserAccountRequest"
            }
          }
        ],
        "tags": [
          "IdentityProvider"
        ]
      }
    }
  },
  "definitions": {
    "pbAccountData": {
      "type": "object",
      "properties": {
        "id": {
          "type": "string",
          "format": "int64"
        },
        "accType": {
          "type": "integer",
          "format": "int32"
        },
        "accountName": {
          "type": "string"
        },
        "owner": {
          "type": "string"
        },
        "bio": {
          "type": "string"
        },
        "status": {
          "type": "string"
        },
        "plan": {
          "type": "integer",
          "format": "int32"
        },
        "avatarUri": {
          "type": "string"
        },
        "plays": {
          "type": "string",
          "format": "int64"
        },
        "likes": {
          "type": "string",
          "format": "int64"
        },
        "follows": {
          "type": "string",
          "format": "int64"
        },
        "shares": {
          "type": "string",
          "format": "int64"
        },
        "createdAt": {
          "type": "string",
          "format": "date-time"
        },
        "updatedAt": {
          "type": "string",
          "format": "date-time"
        },
        "accountType": {
          "$ref": "#/definitions/pbAccountTypeData"
        }
      }
    },
    "pbAccountTypeData": {
      "type": "object",
      "properties": {
        "id": {
          "type": "string",
          "format": "int64"
        },
        "accType": {
          "type": "integer",
          "format": "int32"
        },
        "permissions": {
          "type": "string"
        },
        "isArtist": {
          "type": "boolean"
        },
        "isProducer": {
          "type": "boolean"
        },
        "isWriter": {
          "type": "boolean"
        },
        "isLabel": {
          "type": "boolean"
        },
        "isUser": {
          "type": "boolean"
        },
        "createdAt": {
          "type": "string",
          "format": "date-time"
        },
        "updatedAt": {
          "type": "string",
          "format": "date-time"
        }
      }
    },
    "pbLoggedInUser": {
      "type": "object",
      "properties": {
        "id": {
          "type": "string",
          "format": "int64"
        },
        "username": {
          "type": "string"
        },
        "fullName": {
          "type": "string"
        },
        "email": {
          "type": "string"
        },
        "passwordHash": {
          "type": "string"
        },
        "passwordSalt": {
          "type": "string"
        },
        "countryCode": {
          "type": "string"
        },
        "roleId": {
          "type": "string",
          "format": "int64"
        },
        "status": {
          "type": "string"
        },
        "lastLoginAt": {
          "type": "string",
          "format": "date-time"
        },
        "usernameChangedAt": {
          "type": "string",
          "format": "date-time"
        },
        "emailChangedAt": {
          "type": "string",
          "format": "date-time"
        },
        "passwordChangedAt": {
          "type": "string",
          "format": "date-time"
        },
        "createdAt": {
          "type": "string",
          "format": "date-time"
        },
        "updatedAt": {
          "type": "string",
          "format": "date-time"
        }
      }
    },
    "pbLoginUserAccountRequest": {
      "type": "object",
      "properties": {
        "username": {
          "type": "string"
        },
        "password": {
          "type": "string"
        }
      }
    },
    "pbLoginUserAccountResponse": {
      "type": "object",
      "properties": {
        "loggedInUser": {
          "$ref": "#/definitions/pbLoggedInUser"
        },
        "sessionId": {
          "type": "string"
        },
        "accessToken": {
          "type": "string"
        },
        "refreshToken": {
          "type": "string"
        },
        "accessTokenExpiresAt": {
          "type": "string",
          "format": "date-time"
        },
        "refreshTokenExpiresAt": {
          "type": "string",
          "format": "date-time"
        }
      }
    },
    "pbRegisterUserAccountRequest": {
      "type": "object",
      "properties": {
        "username": {
          "type": "string"
        },
        "fullName": {
          "type": "string"
        },
        "email": {
          "type": "string"
        },
        "password": {
          "type": "string"
        },
        "countryCode": {
          "type": "string"
        },
        "roleId": {
          "type": "integer",
          "format": "int32"
        },
        "status": {
          "type": "string"
        },
        "accountType": {
          "type": "integer",
          "format": "int32"
        },
        "accountName": {
          "type": "string"
        },
        "accountBio": {
          "type": "string"
        },
        "accountPlan": {
          "type": "integer",
          "format": "int32"
        },
        "accountAvatarUri": {
          "type": "string"
        }
      }
    },
    "pbRegisterUserAccountResponse": {
      "type": "object",
      "properties": {
        "userAccount": {
          "$ref": "#/definitions/pbUserAccount"
        }
      }
    },
    "pbUserAccount": {
      "type": "object",
      "properties": {
        "user": {
          "$ref": "#/definitions/pbUserData"
        },
        "account": {
          "$ref": "#/definitions/pbAccountData"
        }
      }
    },
    "pbUserData": {
      "type": "object",
      "properties": {
        "id": {
          "type": "string",
          "format": "int64"
        },
        "username": {
          "type": "string"
        },
        "fullName": {
          "type": "string"
        },
        "email": {
          "type": "string"
        },
        "passwordHash": {
          "type": "string"
        },
        "passwordSalt": {
          "type": "string"
        },
        "countryCode": {
          "type": "string"
        },
        "roleId": {
          "type": "string",
          "format": "int64"
        },
        "status": {
          "type": "string"
        },
        "accountType": {
          "type": "integer",
          "format": "int32"
        },
        "accountName": {
          "type": "string"
        },
        "accountBio": {
          "type": "string"
        },
        "accountPlan": {
          "type": "integer",
          "format": "int32"
        },
        "accountAvatarUri": {
          "type": "string"
        },
        "lastLoginAt": {
          "type": "string",
          "format": "date-time"
        },
        "usernameChangedAt": {
          "type": "string",
          "format": "date-time"
        },
        "emailChangedAt": {
          "type": "string",
          "format": "date-time"
        },
        "passwordChangedAt": {
          "type": "string",
          "format": "date-time"
        },
        "createdAt": {
          "type": "string",
          "format": "date-time"
        },
        "updatedAt": {
          "type": "string",
          "format": "date-time"
        }
      }
    },
    "protobufAny": {
      "type": "object",
      "properties": {
        "@type": {
          "type": "string"
        }
      },
      "additionalProperties": {}
    },
    "rpcStatus": {
      "type": "object",
      "properties": {
        "code": {
          "type": "integer",
          "format": "int32"
        },
        "message": {
          "type": "string"
        },
        "details": {
          "type": "array",
          "items": {
            "type": "object",
            "$ref": "#/definitions/protobufAny"
          }
        }
      }
    }
  }
}
